klean/__init__.py
klean/cli.py
klean/config_generator.py
klean/discovery.py
klean/hooks.py
klean/model_defaults.py
klean/model_utils.py
klean/platform.py
klean/reviews.py
klean/data/agents/TEMPLATE.md
klean/data/agents/arm-cortex-expert.md
klean/data/agents/c-pro.md
klean/data/agents/code-reviewer.md
klean/data/agents/debugger.md
klean/data/agents/orchestrator.md
klean/data/agents/performance-engineer.md
klean/data/agents/rust-expert.md
klean/data/agents/security-auditor.md
klean/data/commands/kln/agent.md
klean/data/commands/kln/doc.md
klean/data/commands/kln/help.md
klean/data/commands/kln/learn.md
klean/data/commands/kln/multi.md
klean/data/commands/kln/quick.md
klean/data/commands/kln/remember.md
klean/data/commands/kln/rethink.md
klean/data/commands/kln/status.md
klean/data/config/CLAUDE.md
klean/data/config/litellm/.env.example
klean/data/config/litellm/config.yaml
klean/data/config/litellm/openrouter.yaml
klean/data/core/config.yaml
klean/data/core/klean_core.py
klean/data/core/prompts/agent-base.md
klean/data/core/prompts/format-json.md
klean/data/core/prompts/format-text.md
klean/data/core/prompts/rethink.md
klean/data/core/prompts/review.md
klean/data/core/prompts/roles/architect.md
klean/data/core/prompts/roles/auditor.md
klean/data/core/prompts/roles/coder.md
klean/data/core/prompts/roles/researcher.md
klean/data/core/prompts/roles/reviewer.md
klean/data/multi-agents/analyzer.md
klean/data/multi-agents/code_analyzer.md
klean/data/multi-agents/file_scout.md
klean/data/multi-agents/manager.md
klean/data/multi-agents/security_auditor.md
klean/data/multi-agents/synthesizer.md
klean/data/prompts/review.md
klean/data/rules/kln.md
klean/data/scripts/kb_utils.py
klean/data/scripts/klean-statusline.py
klean/data/scripts/knowledge-capture.py
klean/data/scripts/knowledge-events.py
klean/data/scripts/knowledge-search.py
klean/data/scripts/knowledge-server.py
klean/data/scripts/knowledge_db.py
klean/data/scripts/prepare-release.sh
klean/data/scripts/smart-capture.py
kln_ai-1.0.0b7.dist-info/licenses/LICENSE
kln_ai-1.0.0b7.dist-info/METADATA
kln_ai-1.0.0b7.dist-info/WHEEL
kln_ai-1.0.0b7.dist-info/entry_points.txt
kln_ai-1.0.0b7.dist-info/top_level.txt
kln_ai-1.0.0b7.dist-info/RECORD
