Metadata-Version: 2.4
Name: kln-ai
Version: 1.0.0b7
Summary: Multi-model code review and knowledge capture system for Claude Code
Author-email: Calin Faja <calinfaja@gmail.com>
License: Apache-2.0
Project-URL: Homepage, https://github.com/calinfaja/k-lean
Project-URL: Documentation, https://github.com/calinfaja/k-lean#readme
Project-URL: Repository, https://github.com/calinfaja/k-lean
Project-URL: Issues, https://github.com/calinfaja/k-lean/issues
Keywords: claude,code-review,ai,llm,cli,knowledge-base
Classifier: Development Status :: 4 - Beta
Classifier: Environment :: Console
Classifier: Intended Audience :: Developers
Classifier: License :: OSI Approved :: Apache Software License
Classifier: Operating System :: OS Independent
Classifier: Operating System :: POSIX :: Linux
Classifier: Operating System :: MacOS
Classifier: Operating System :: Microsoft :: Windows
Classifier: Programming Language :: Python :: 3
Classifier: Programming Language :: Python :: 3.9
Classifier: Programming Language :: Python :: 3.10
Classifier: Programming Language :: Python :: 3.11
Classifier: Programming Language :: Python :: 3.12
Classifier: Topic :: Software Development :: Quality Assurance
Classifier: Topic :: Software Development :: Testing
Requires-Python: >=3.9
License-File: LICENSE
Requires-Dist: click>=8.0.0
Requires-Dist: rich>=13.0.0
Requires-Dist: pyyaml>=6.0.0
Requires-Dist: httpx>=0.27.0
Requires-Dist: psutil>=5.9.0
Requires-Dist: platformdirs>=4.0.0
Requires-Dist: fastembed>=0.3.0
Requires-Dist: numpy>=1.24.0
Requires-Dist: smolagents[litellm]>=1.17.0
Requires-Dist: litellm[proxy]>=1.0.0; sys_platform != "win32"
Requires-Dist: litellm>=1.0.0; sys_platform == "win32"
Requires-Dist: hypercorn>=0.14.0; sys_platform == "win32"
Requires-Dist: ddgs>=6.0.0
Requires-Dist: markdownify>=0.11.0
Requires-Dist: lizard>=1.17.0
Provides-Extra: agent-sdk
Requires-Dist: anthropic<1.0.0,>=0.34.0; extra == "agent-sdk"
Provides-Extra: telemetry
Requires-Dist: arize-phoenix>=4.0; extra == "telemetry"
Requires-Dist: opentelemetry-sdk; extra == "telemetry"
Requires-Dist: opentelemetry-exporter-otlp; extra == "telemetry"
Requires-Dist: openinference-instrumentation-smolagents; extra == "telemetry"
Provides-Extra: toon
Requires-Dist: python-toon>=0.1.0; extra == "toon"
Provides-Extra: all
Requires-Dist: kln-ai[agent-sdk,telemetry,toon]; extra == "all"
Provides-Extra: dev
Requires-Dist: pytest>=7.0.0; extra == "dev"
Requires-Dist: pytest-cov>=4.0.0; extra == "dev"
Requires-Dist: black>=23.0.0; extra == "dev"
Requires-Dist: ruff>=0.1.0; extra == "dev"
Dynamic: license-file
